<?xml version="1.0" encoding="utf-8"?>
<!DOCTYPE documentInfo>
<documentInfo url="/home/tushar/t/learn/B S Grewal Maths.pdf">
 <generalInfo>
  <history>
   <oldPage viewport="170;C2:0.499736:0.460243:1"/>
   <oldPage viewport="171;C2:0.499736:0.881339:1"/>
   <oldPage viewport="173;C2:0.499736:0.29716:1"/>
   <oldPage viewport="174;C2:0.499736:0.718256:1"/>
   <oldPage viewport="176;C2:0.499736:0.134077:1"/>
   <oldPage viewport="177;C2:0.499736:0.554767:1"/>
   <oldPage viewport="178;C2:0.499736:0.975862:1"/>
   <oldPage viewport="180;C2:0.499736:1.00142:1"/>
   <oldPage viewport="181;C2:0.499736:0.00182556:1"/>
   <oldPage viewport="180;C2:0.499736:1.00223:1"/>
   <current viewport="181;C2:0.499601:0.601716:1"/>
  </history>
  <views>
   <view name="PageView">
    <zoom mode="1" value="1.02772"/>
    <continuous mode="1"/>
    <viewMode mode="0"/>
    <trimMargins value="0"/>
   </view>
  </views>
 </generalInfo>
</documentInfo>
