<?xml version="1.0" encoding="utf-8"?>
<!DOCTYPE documentInfo>
<documentInfo url="/home/tushar/Downloads/DC_M4.pdf">
 <generalInfo>
  <history>
   <oldPage viewport="58;C2:0.499736:0.993692:1"/>
   <oldPage viewport="59;C2:0.499736:0.984787:1"/>
   <oldPage viewport="60;C2:0.499736:0.99295:1"/>
   <oldPage viewport="61;C2:0.499736:0.408163:1"/>
   <oldPage viewport="0;C2:0.499736:0.18337:1"/>
   <oldPage viewport="1;C2:0.499736:0.348052:1"/>
   <oldPage viewport="3;C2:0.499736:0.627087:1"/>
   <oldPage viewport="57;C2:0.499736:0.679777:1"/>
   <oldPage viewport="58;C2:0.499736:0.977365:1"/>
   <oldPage viewport="59;C2:0.499736:0.997403:1"/>
   <current viewport="60;C2:0.499736:0.325788:1"/>
  </history>
  <views>
   <view name="PageView">
    <zoom mode="1" value="1.59643"/>
    <continuous mode="1"/>
    <viewMode mode="0"/>
    <trimMargins value="0"/>
   </view>
  </views>
 </generalInfo>
</documentInfo>
