<?xml version="1.0" encoding="utf-8"?>
<!DOCTYPE documentInfo>
<documentInfo url="/home/tushar/mass/dc assignment 1by18cs188.pdf">
 <generalInfo>
  <history>
   <oldPage viewport="0;C2:0.499601:0.99256:1"/>
   <oldPage viewport="1;C2:0.499601:0.984472:1"/>
   <oldPage viewport="2;C2:0.499601:0.0684053:1"/>
   <oldPage viewport="1;C2:0.499601:-0.00488021:1"/>
   <oldPage viewport="0;C2:0.499601:0.979869:1"/>
   <oldPage viewport="1;C2:0.499601:-0.000887311:1"/>
   <oldPage viewport="0;C2:0.499601:0.994311:1"/>
   <current viewport="1;C2:0.499601:0.212511:1"/>
  </history>
  <views>
   <view name="PageView">
    <zoom mode="1" value="1.41979"/>
    <continuous mode="1"/>
    <viewMode mode="0"/>
    <trimMargins value="0"/>
   </view>
  </views>
 </generalInfo>
</documentInfo>
